hnclient/__init__.py
hnclient/client.py
hnclient/session.py
hnclient/set_api.py
hnclient/utils.py
hnclient-0.0.2.dist-info/LICENSE
hnclient-0.0.2.dist-info/METADATA
hnclient-0.0.2.dist-info/WHEEL
hnclient-0.0.2.dist-info/top_level.txt
hnclient-0.0.2.dist-info/RECORD
