Metadata-Version: 2.1
Name: hnclient
Version: 0.0.2
Summary: Python client for Hacker News API with cached API calls built in.
Home-page: UNKNOWN
Author: InquestGeronimmo
Author-email: rcostanl@gmail.com
License: UNKNOWN
Keywords: python,hacker-news,api
Platform: UNKNOWN
Classifier: Development Status :: 5 - Production/Stable
Classifier: Intended Audience :: Developers
Classifier: Programming Language :: Python :: 3
Classifier: Operating System :: Unix
License-File: LICENSE
Requires-Dist: requests-cache >=1.1.1
